[{"desc":"北北基","no":"10001000000","n":[{"desc":"公立","no":"10001002000","n":[{"desc":"國立臺灣大學","no":"10001002001"},{"desc":"國立臺灣師範大學","no":"10001002002"},{"desc":"國立政治大學","no":"10001002006"},{"desc":"國立臺灣海洋大學","no":"10001002021"},{"desc":"國立陽明大學","no":"10001002025"},{"desc":"國立臺北藝術大學","no":"10001002028"},{"desc":"國立臺北教育大學","no":"10001002032"},{"desc":"臺北市立大學","no":"10001002035"},{"desc":"國立臺灣藝術大學","no":"10001002056"},{"desc":"國立臺北大學","no":"10001002099"}]},{"desc":"私立","no":"10001001000","n":[{"desc":"東吳大學","no":"10001001005"},{"desc":"淡江大學","no":"10001001014"},{"desc":"中國文化大學","no":"10001001017"},{"desc":"大同大學","no":"10001001019"},{"desc":"輔仁大學","no":"10001001020"},{"desc":"華梵大學","no":"10001001044"},{"desc":"銘傳大學","no":"10001001046"},{"desc":"世新大學","no":"10001001047"},{"desc":"實踐大學","no":"10001001050"},{"desc":"真理大學","no":"10001001079"},{"desc":"臺北醫學大學","no":"10001001109"},{"desc":"馬偕醫學院","no":"10001001152"},{"desc":"臺北基督學院","no":"10001001154"}]}]},{"desc":"桃竹苗","no":"10002000000","n":[{"desc":"公立","no":"10002002000","n":[{"desc":"國立清華大學","no":"10002002011"},{"desc":"國立交通大學","no":"10002002013"},{"desc":"國立中央大學","no":"10002002016"},{"desc":"國立體育大學","no":"10002002039"},{"desc":"國立聯合大學","no":"10002002151"}]},{"desc":"私立","no":"10002001000","n":[{"desc":"中原大學","no":"10002001008"},{"desc":"長庚大學","no":"10002001030"},{"desc":"元智大學","no":"10002001040"},{"desc":"中華大學","no":"10002001043"},{"desc":"玄奘大學","no":"10002001065"},{"desc":"開南大學","no":"10002001110"}]}]},{"desc":"中彰投","no":"10003000000","n":[{"desc":"公立","no":"10003002000","n":[{"desc":"國立中興大學","no":"10003002003"},{"desc":"國立彰化師範大學","no":"10003002023"},{"desc":"國立臺中教育大學","no":"10003002031"},{"desc":"國立暨南國際大學","no":"10003002058"},{"desc":"國立臺灣體育運動大學","no":"10003002060"}]},{"desc":"私立","no":"10003001000","n":[{"desc":"東海大學","no":"10003001009"},{"desc":"中國醫藥大學","no":"10003001012"},{"desc":"逢甲大學","no":"10003001015"},{"desc":"靜宜大學","no":"10003001018"},{"desc":"中山醫學大學","no":"10003001026"},{"desc":"大葉大學","no":"10003001042"},{"desc":"明道大學","no":"10003001133"},{"desc":"亞洲大學","no":"10003001134"}]}]},{"desc":"雲嘉南","no":"10004000000","n":[{"desc":"公立","no":"10004002000","n":[{"desc":"國立成功大學","no":"10004002004"},{"desc":"國立臺南大學","no":"10004002033"},{"desc":"國立中正大學","no":"10004002041"},{"desc":"國立臺南藝術大學","no":"10004002063"},{"desc":"國立嘉義大學","no":"10004002100"}]},{"desc":"私立","no":"10004001000","n":[{"desc":"長榮大學","no":"10004001051"},{"desc":"南華大學","no":"10004001059"},{"desc":"台灣首府大學","no":"10004001111"},{"desc":"康寧大學","no":"10004001112"},{"desc":"中信金融管理學院","no":"10004001113"}]}]},{"desc":"高屏金","no":"10005000000","n":[{"desc":"公立","no":"10005002000","n":[{"desc":"國立高雄師範大學","no":"10005002022"},{"desc":"國立中山大學","no":"10005002027"},{"desc":"國立屏東大學","no":"10005002036"},{"desc":"國立高雄大學","no":"10005002101"},{"desc":"國立金門大學","no":"10005002153"}]},{"desc":"私立","no":"10005001000","n":[{"desc":"高雄醫學大學","no":"10005001007"},{"desc":"義守大學","no":"10005001045"}]}]},{"desc":"宜花東","no":"10006000000","n":[{"desc":"公立","no":"10006002000","n":[{"desc":"國立東華大學","no":"10006002034"},{"desc":"國立臺東大學","no":"10006002038"},{"desc":"國立宜蘭大學","no":"10006002150"}]},{"desc":"私立","no":"10006001000","n":[{"desc":"慈濟大學","no":"10006001108"},{"desc":"佛光大學","no":"10006001130"}]}]}]